gslibutils/__init__.py
gslibutils/gslib2csv.py
gslibutils/parser.py
gslibutils/writer.py
gslibutils-0.1.0.dist-info/LICENSE
gslibutils-0.1.0.dist-info/WHEEL
gslibutils-0.1.0.dist-info/METADATA
gslibutils-0.1.0.dist-info/RECORD
