Metadata-Version: 2.1
Name: gslibutils
Version: 0.1.0
Summary: Contains utilities to load/save GSLIB files, such as
Home-page: https://github.com/exepulveda/gslibutils
Author: Exequiel Sepúlveda
Author-email: esepulveda@protonmail.com
Requires-Python: >=3.6
Classifier: Intended Audience :: Information Technology
Classifier: Intended Audience :: System Administrators
Classifier: Operating System :: OS Independent
Classifier: Programming Language :: Python :: 3
Classifier: Programming Language :: Python
Classifier: Topic :: Software Development :: Libraries :: Python Modules
Classifier: Topic :: Software Development :: Libraries
Classifier: Topic :: Software Development
Classifier: Typing :: Typed
Classifier: Development Status :: 4 - Beta
Classifier: Intended Audience :: Developers
Classifier: Programming Language :: Python :: 3 :: Only
Classifier: Programming Language :: Python :: 3.6
Classifier: Programming Language :: Python :: 3.7
Classifier: Programming Language :: Python :: 3.8
Classifier: Programming Language :: Python :: 3.9
Classifier: License :: OSI Approved :: MIT License
Requires-Dist: typer >= 0.3.0
Requires-Dist: numpy >= 1.19.0
Requires-Dist: pandas >= 1.3.0
Requires-Dist: colorama >=0.4.3,<0.5.0 ; extra == "all"
Requires-Dist: shellingham >=1.3.0,<2.0.0 ; extra == "all"
Requires-Dist: autoflake >=1.3.1,<2.0.0 ; extra == "dev"
Requires-Dist: flake8 >=3.8.3,<4.0.0 ; extra == "dev"
Requires-Dist: mkdocs >=1.1.2,<2.0.0 ; extra == "doc"
Requires-Dist: mkdocs-material >=5.4.0,<6.0.0 ; extra == "doc"
Requires-Dist: markdown-include >=0.5.1,<0.6.0 ; extra == "doc"
Requires-Dist: pytest >=4.4.0,<5.4.0 ; extra == "test"
Requires-Dist: pytest-cov >=2.10.0,<3.0.0 ; extra == "test"
Requires-Dist: coverage >=5.2,<6.0 ; extra == "test"
Provides-Extra: all
Provides-Extra: dev
Provides-Extra: doc
Provides-Extra: test
